plone.app.intid-2.0.1-py3.13-nspkg.pth
plone/app/intid/__init__.py
plone/app/intid/configure.zcml
plone/app/intid/profiles.zcml
plone/app/intid/setuphandlers.py
plone/app/intid/testing.py
plone/app/intid/profiles/default/install_intids.txt
plone/app/intid/profiles/default/intid_register_content.txt
plone/app/intid/profiles/default/metadata.xml
plone/app/intid/tests/__init__.py
plone/app/intid/tests/test_setup.py
plone_app_intid-2.0.1.dist-info/licenses/LICENSE.GPL
plone_app_intid-2.0.1.dist-info/licenses/LICENSE.txt
plone_app_intid-2.0.1.dist-info/METADATA
plone_app_intid-2.0.1.dist-info/WHEEL
plone_app_intid-2.0.1.dist-info/entry_points.txt
plone_app_intid-2.0.1.dist-info/namespace_packages.txt
plone_app_intid-2.0.1.dist-info/top_level.txt
plone_app_intid-2.0.1.dist-info/RECORD
