Metadata-Version: 2.4
Name: plone.app.intid
Version: 2.0.1
Summary: Installation and migration support for five.intid within Plone/CMF
Home-page: https://github.com/plone/plone.app.intid
Author: Alec Mitchell
Author-email: apm13@columbia.edu
License: GPL
Keywords: plone zope five intid
Classifier: Development Status :: 5 - Production/Stable
Classifier: Framework :: Plone
Classifier: Framework :: Plone :: 6.0
Classifier: Framework :: Plone :: Core
Classifier: License :: OSI Approved :: GNU General Public License (GPL)
Classifier: Programming Language :: Python
Classifier: Programming Language :: Python :: 3.8
Classifier: Programming Language :: Python :: 3.9
Classifier: Programming Language :: Python :: 3.10
Classifier: Programming Language :: Python :: 3.11
Requires-Python: >=3.8
License-File: LICENSE.GPL
License-File: LICENSE.txt
Requires-Dist: setuptools
Requires-Dist: five.intid>=1.0
Requires-Dist: Products.CMFCore
Requires-Dist: Products.GenericSetup
Requires-Dist: zope.component
Requires-Dist: zope.intid
Requires-Dist: zope.lifecycleevent
Provides-Extra: test
Requires-Dist: plone.app.testing; extra == "test"
Requires-Dist: plone.dexterity; extra == "test"
Dynamic: author
Dynamic: author-email
Dynamic: classifier
Dynamic: description
Dynamic: description-content-type
Dynamic: home-page
Dynamic: keywords
Dynamic: license
Dynamic: license-file
Dynamic: provides-extra
Dynamic: requires-dist
Dynamic: requires-python
Dynamic: summary
